carbon/__init__.py
carbon/carbon.py
carbon/errors.py
carbon/opts.py
carbon/utils.py
py_carbon-1.0.4.dist-info/LICENSE
py_carbon-1.0.4.dist-info/METADATA
py_carbon-1.0.4.dist-info/WHEEL
py_carbon-1.0.4.dist-info/top_level.txt
py_carbon-1.0.4.dist-info/RECORD
