Metadata-Version: 2.1
Name: py-carbon
Version: 1.0.4
Summary: Fully asynchronous Python library for carbon.now.sh
Home-page: https://github.com/itsmewulf/py-carbon
Author: wulf
Author-email: paul@przybyszew.ski
License: MIT
Classifier: Programming Language :: Python :: 3
Classifier: License :: OSI Approved :: MIT License
Requires-Python: >=3.9
License-File: LICENSE
